Metadata-Version: 2.4
Name: llama-mlx-pipeline-llamasearch
Version: 0.1.0
Summary: Data processing pipeline using MLX (scraper, chunker, extractor).
Project-URL: Homepage, https://github.com/llama-ai/llama-mlx-pipeline
Author-email: llama-mlx-pipeline-llamasearch <nikjois@llamasearch.ai>
License: MIT
License-File: LICENSE
Keywords: chunker,extractor,llama,mlx,pipeline,scraper
Classifier: Development Status :: 3 - Alpha
Classifier: Intended Audience :: Developers
Classifier: License :: OSI Approved :: MIT License
Classifier: Programming Language :: Python :: 3
Requires-Python: >=3.8
Requires-Dist: beautifulsoup4>=4.9.3
Requires-Dist: cchardet>=2.1.7
Requires-Dist: cryptography>=36.0.0
Requires-Dist: dataclasses-json>=0.5.7
Requires-Dist: html2text>=2020.1.16
Requires-Dist: iso8601>=1.0.2
Requires-Dist: lxml>=4.6.3
Requires-Dist: mlx-lm>=0.1.0
Requires-Dist: mlx>=0.5.0
Requires-Dist: numpy>=1.21.3
Requires-Dist: pillow>=8.3.2
Requires-Dist: playwright>=1.22.0
Requires-Dist: progressbar2>=4.0.0
Requires-Dist: pybase64>=1.2.1
Requires-Dist: pydantic>=1.8.2
Requires-Dist: pymupdf>=1.18.19
Requires-Dist: pypandoc>=1.5
Requires-Dist: pytesseract>=0.3.8
Requires-Dist: python-docx>=0.8.11
Requires-Dist: python-frontmatter>=1.0.0
Requires-Dist: python-magic>=0.4.27
Requires-Dist: python-pptx>=0.6.21
Requires-Dist: python-slugify>=6.1.2
Requires-Dist: regex>=2021.10.8
Requires-Dist: requests-html>=0.10.0
Requires-Dist: requests-toolbelt>=0.9.1
Requires-Dist: requests>=2.26.0
Requires-Dist: tqdm>=4.62.3
Requires-Dist: trafilatura>=1.4.0
Requires-Dist: url-normalize>=1.4.3
Requires-Dist: validators>=0.20.0
Provides-Extra: dev
Requires-Dist: black>=23.0.0; extra == 'dev'
Requires-Dist: isort>=5.12.0; extra == 'dev'
Requires-Dist: mypy>=1.0.0; extra == 'dev'
Requires-Dist: pytest>=7.0.0; extra == 'dev'
Requires-Dist: ruff>=0.1.0; extra == 'dev'
